MANIFEST.in
README.rst
setup.py
docs/HISTORY.txt
docs/LICENSE.GPL
docs/LICENSE.txt
docs/screenshot_default.png
docs/screenshot_onegov.png
ftw/__init__.py
ftw.slider.egg-info/PKG-INFO
ftw.slider.egg-info/SOURCES.txt
ftw.slider.egg-info/dependency_links.txt
ftw.slider.egg-info/entry_points.txt
ftw.slider.egg-info/namespace_packages.txt
ftw.slider.egg-info/not-zip-safe
ftw.slider.egg-info/requires.txt
ftw.slider.egg-info/top_level.txt
ftw/slider/__init__.py
ftw/slider/configure.zcml
ftw/slider/interfaces.py
ftw/slider/lawgiver.zcml
ftw/slider/permissions.zcml
ftw/slider/resources.zcml
ftw/slider/testing.py
ftw/slider/browser/__init__.py
ftw/slider/browser/configure.zcml
ftw/slider/browser/pane.pt
ftw/slider/browser/pane.py
ftw/slider/browser/slider.pt
ftw/slider/browser/slider.py
ftw/slider/browser/utils.py
ftw/slider/browser/resources/ajax-loader.gif
ftw/slider/browser/resources/ftwtheming.scss
ftw/slider/browser/resources/main.css
ftw/slider/browser/resources/main.js
ftw/slider/browser/resources/onegovtheme.sass
ftw/slider/browser/resources/slick.css
ftw/slider/browser/resources/slick.js
ftw/slider/browser/resources/slick.min.js
ftw/slider/browser/resources/slider-compiled.css
ftw/slider/browser/resources/slider-compiled.js
ftw/slider/browser/resources/slider.css
ftw/slider/browser/resources/slider.js
ftw/slider/browser/resources/slider_block.png
ftw/slider/browser/resources/slider_pane.png
ftw/slider/contents/__init__.py
ftw/slider/contents/container.py
ftw/slider/contents/pane.py
ftw/slider/locales/ftw.slider.pot
ftw/slider/locales/plone.pot
ftw/slider/locales/de/LC_MESSAGES/ftw.slider.po
ftw/slider/locales/de/LC_MESSAGES/plone.po
ftw/slider/profiles/default/cssregistry.xml
ftw/slider/profiles/default/jsregistry.xml
ftw/slider/profiles/default/metadata.xml
ftw/slider/profiles/default/propertiestool.xml
ftw/slider/profiles/default/rolemap.xml
ftw/slider/profiles/default/types.xml
ftw/slider/profiles/default/types/ftw.slider.Container.xml
ftw/slider/profiles/default/types/ftw.slider.Pane.xml
ftw/slider/profiles/default_plone5/metadata.xml
ftw/slider/profiles/default_plone5/registry.xml
ftw/slider/profiles/default_plone5/rolemap.xml
ftw/slider/profiles/default_plone5/types.xml
ftw/slider/profiles/default_plone5/types/ftw.slider.Container.xml
