Metadata-Version: 2.1
Name: ftw.slider
Version: 3.5.0
Summary: Slider content type for Plone.
Home-page: https://github.com/4teamwork/ftw.slider
Author: 4teamwork AG
Author-email: mailto:info@4teamwork.ch
License: GPL2
Platform: UNKNOWN
Classifier: Framework :: Plone :: 4.3
Classifier: Framework :: Plone :: 5.1
Classifier: Framework :: Plone
Classifier: Programming Language :: Python
Provides-Extra: tests
